AUTHORS.rst
CONTRIBUTING.rst
HISTORY.rst
LICENSE
MANIFEST.in
setup.py
pytopol/__init__.py
pytopol.egg-info/PKG-INFO
pytopol.egg-info/SOURCES.txt
pytopol.egg-info/dependency_links.txt
pytopol.egg-info/not-zip-safe
pytopol.egg-info/top_level.txt
pytopol/general/__init__.py
pytopol/general/utils.py
pytopol/parsers/__init__.py
pytopol/parsers/blocks.py
pytopol/parsers/charmmpar.py
pytopol/parsers/grotop.py
pytopol/parsers/par.py
pytopol/parsers/pdb.py
pytopol/parsers/psf.py
pytopol/parsers/utils.py
scripts/psf2top.py
test/__init__.py
test/config.py
test/test_par_parser.py
test/test_psf_parser.py
test/test_pytopol.py