Metadata-Version: 1.1
Name: pytopol
Version: 0.1.7
Summary: "Library for converting molecular topologies"
Home-page: https://github.com/resal81/pytopol
Author: Reza Salari
Author-email: rezasalari@rutgers.edu
License: GPLv3
Keywords: pytopol
Platform: UNKNOWN
Classifier: Development Status :: 3 - Alpha
Classifier: Intended Audience :: Developers
Classifier: License :: OSI Approved :: GNU General Public License v3 (GPLv3)
Classifier: Natural Language :: English
Classifier: Programming Language :: Python :: 2
Classifier: Programming Language :: Python :: 2.7
